pymab/__init__.py
pymab/game.py
pymab/logging.json
pymab/logging_config.py
pymab/plot_config.py
pymab/reward_distribution.py
pymab/static.py
pymab/policies/__init__.py
pymab/policies/bayesian_ucb.py
pymab/policies/contextual_bandits.py
pymab/policies/epsilon_greedy.py
pymab/policies/gradient.py
pymab/policies/greedy.py
pymab/policies/policy.py
pymab/policies/softmax_selection.py
pymab/policies/thompson_sampling.py
pymab/policies/ucb.py
pymab/policies/mixins/__init__.py
pymab/policies/mixins/stationarity_mixins.py
tests/policies/__init__.py
tests/policies/test_bayesian_ucb.py
tests/policies/test_contextual_bandits.py
tests/policies/test_epsilon_greedy.py
tests/policies/test_gradient.py
tests/policies/test_greedy.py
tests/policies/test_policy.py
tests/policies/test_softmax_selection.py
tests/policies/test_thompson_sampling.py
tests/policies/test_ucb.py
pymab-0.1.0.dist-info/LICENSE
pymab-0.1.0.dist-info/METADATA
pymab-0.1.0.dist-info/WHEEL
pymab-0.1.0.dist-info/top_level.txt
pymab-0.1.0.dist-info/RECORD
