Metadata-Version: 2.1
Name: pymab
Version: 0.1.0
Summary: A Python library for reinforcement learning algorithms.
Home-page: https://github.com/danielaLopes/pymab
Author: Daniela Lopes
Author-email: danielalopes_97@hotmail.com
Classifier: Programming Language :: Python :: 3
Classifier: License :: OSI Approved :: MIT License
Classifier: Operating System :: OS Independent
Requires-Python: >=3.6
License-File: LICENSE
Requires-Dist: joblib
Requires-Dist: matplotlib
Requires-Dist: numpy
Requires-Dist: pandas
Requires-Dist: plotly
Requires-Dist: scipy
Requires-Dist: tqdm
